{
    "url": "https://www.chess.com/game/live/69017453025",
    "pgn": "[Event \"Live Chess\"]\n[Site \"Chess.com\"]\n[Date \"2023.02.01\"]\n[Round \"-\"]\n[White \"Metamorf65\"]\n[Black \"pogiboydge\"]\n[Result \"0-1\"]\n[CurrentPosition \"r1bq1rk1/p1p2pp1/1pn4p/2p1p3/2B1P2P/P1NP1N2/2P2KP1/R1B5 b - -\"]\n[Timezone \"UTC\"]\n[ECO \"C23\"]\n[ECOUrl \"https://www.chess.com/openings/Bishops-Opening\"]\n[UTCDate \"2023.02.01\"]\n[UTCTime \"19:04:45\"]\n[WhiteElo \"834\"]\n[BlackElo \"808\"]\n[TimeControl \"600\"]\n[Termination \"pogiboydge won by resignation\"]\n[StartTime \"19:04:45\"]\n[EndDate \"2023.02.01\"]\n[EndTime \"19:09:41\"]\n[Link \"https://www.chess.com/game/live/69017453025\"]\n\n1. e4 {[%clk 0:10:00]} 1... e5 {[%clk 0:09:59.9]} 2. Bc4 {[%clk 0:09:58.7]} 2... Nc6 {[%clk 0:09:57]} 3. d3 {[%clk 0:09:57.8]} 3... Nf6 {[%clk 0:09:53.6]} 4. Nc3 {[%clk 0:09:56.1]} 4... Bc5 {[%clk 0:09:33.5]} 5. Nf3 {[%clk 0:09:54.1]} 5... d6 {[%clk 0:09:28.7]} 6. Ng5 {[%clk 0:09:51.9]} 6... O-O {[%clk 0:09:12.4]} 7. h4 {[%clk 0:09:41]} 7... h6 {[%clk 0:09:06.1]} 8. Nf3 {[%clk 0:09:39.2]} 8... b6 {[%clk 0:08:40.4]} 9. a3 {[%clk 0:09:30]} 9... Ng4 {[%clk 0:07:46.4]} 10. b4 {[%clk 0:09:21]} 10... Nxf2 {[%clk 0:07:42.9]} 11. Qe2 {[%clk 0:09:08.2]} 11... Nxh1 {[%clk 0:07:41.3]} 12. bxc5 {[%clk 0:09:06.5]} 12... dxc5 {[%clk 0:07:28.4]} 13. Qf1 {[%clk 0:08:58.1]} 13... Ng3 {[%clk 0:07:08]} 14. Qf2 {[%clk 0:08:56.2]} 14... Nh1 {[%clk 0:06:42.2]} 15. Kf1 {[%clk 0:08:52.9]} 15... Nxf2 {[%clk 0:06:23.8]} 16. Kxf2 {[%clk 0:08:51]} 0-1\n",
    "time_control": "600",
    "end_time": 1675278581,
    "rated": true,
    "tcn": "mC0KfA5Qlt!Tbs9IgvZRvM8!pF3VMvXPiqTEjzEndmnhzIRImfhwfnwhefhnfn",
    "uuid": "467332e6-a263-11ed-8d9d-78ac4409ff3c",
    "initial_setup": "rnbqkbnr/pppppppp/8/8/8/8/PPPPPPPP/RNBQKBNR w KQkq - 0 1",
    "fen": "r1bq1rk1/p1p2pp1/1pn4p/2p1p3/2B1P2P/P1NP1N2/2P2KP1/R1B5 b - -",
    "time_class": "rapid",
    "rules": "chess",
    "white": {
        "rating": 834,
        "result": "resigned",
        "@id": "https://api.chess.com/pub/player/metamorf65",
        "username": "Metamorf65",
        "uuid": "3090c3f4-6803-11ec-86ec-5351cc48347e"
    },
    "black": {
        "rating": 808,
        "result": "win",
        "@id": "https://api.chess.com/pub/player/pogiboydge",
        "username": "pogiboydge",
        "uuid": "860315be-91d1-11ed-9b31-bff4cf59842c"
    }
}